{
  "appPageId" : "5f3496ad-333d-4427-9210-776490b7cc27",
  "componentName" : "siteforce:sldsOneColLayout",
  "dataProviders" : [ ],
  "id" : "36e917ca-4e57-4887-b481-b25f0460b417",
  "label" : "Brokerage Receipt Detail",
  "regions" : [ {
    "id" : "247e87fd-be10-4963-ac9c-52f2eca9f15a",
    "regionName" : "header",
    "type" : "region"
  }, {
    "components" : [ {
      "componentAttributes" : {
        "recordId" : "{!recordId}"
      },
      "componentName" : "forceCommunity:recordHeadline",
      "id" : "3974fb9f-d574-4165-821a-1d17907f0ef1",
      "renderPriority" : "NEUTRAL",
      "renditionMap" : { },
      "type" : "component"
    }, {
      "componentAttributes" : {
        "detailsTabLabel" : "Details",
        "discussionsTabLabel" : "Feed",
        "recordId" : "{!recordId}",
        "relatedTabLabel" : "Related",
        "tab1Type" : "details",
        "tab2Type" : "none",
        "tab3Type" : "none",
        "tab4Type" : "none",
        "timelineTabLabel" : "Activity"
      },
      "componentName" : "forceCommunity:recordHomeTabs",
      "id" : "85d92235-9d8d-4db2-8e32-397c37c4fc0e",
      "renderPriority" : "NEUTRAL",
      "renditionMap" : { },
      "type" : "component"
    } ],
    "id" : "1db333bc-61ce-4bcc-8ce7-fa4fac47af03",
    "regionName" : "content",
    "type" : "region"
  }, {
    "id" : "0a1b0f22-41d7-4c13-87ae-9565824de036",
    "regionName" : "footer",
    "type" : "region"
  }, {
    "components" : [ {
      "componentAttributes" : {
        "customHeadTags" : "",
        "description" : "",
        "title" : "{!Record._Object}: {!Record._Title}"
      },
      "componentName" : "forceCommunity:seoAssistant",
      "id" : "4ccd7834-68f5-4b7c-b309-18cf0f6142d5",
      "renditionMap" : { },
      "type" : "component"
    } ],
    "id" : "86c411da-8cba-442d-9fd6-41121f4cb451",
    "regionName" : "sfdcHiddenRegion",
    "type" : "region"
  } ],
  "themeLayoutType" : "Inner",
  "type" : "view",
  "viewType" : "detail-a2g"
}