{
  "appPageId" : "199817ad-97f1-4978-8428-c37fa787150b",
  "componentName" : "siteforce:sldsTwoCol84Layout",
  "dataProviders" : [ ],
  "id" : "736f703f-d3f1-4b1e-9a4f-976223d66479",
  "label" : "Article Detail",
  "regions" : [ {
    "id" : "f726f88e-ee12-4279-91f0-da7cffe7c1ad",
    "regionName" : "header",
    "type" : "region"
  }, {
    "components" : [ {
      "componentAttributes" : {
        "uniqueNameOrId" : "{!urlName}"
      },
      "componentName" : "forceCommunity:breadcrumbs",
      "id" : "00adc805-2c38-4ae8-a8e1-2fc019a9cfe8",
      "renderPriority" : "NEUTRAL",
      "renditionMap" : { },
      "type" : "component"
    }, {
      "componentAttributes" : {
        "enableFeedback" : false,
        "enableVoting" : true,
        "recordId" : "{!recordId}",
        "showTitleInArticleHeader" : true,
        "showTopicPills" : true,
        "urlName" : "{!urlName}"
      },
      "componentName" : "selfService:singleArticleView",
      "id" : "4b94e6ce-005a-475d-a805-07c746a3e1f5",
      "renderPriority" : "NEUTRAL",
      "renditionMap" : { },
      "type" : "component"
    }, {
      "componentAttributes" : {
        "context" : "RECORD",
        "recordId" : "{!recordId}",
        "width" : "WIDE"
      },
      "componentName" : "forceCommunity:feedPublisher",
      "id" : "7a8a93fb-1030-480b-87aa-5c88e80810f2",
      "renderPriority" : "NEUTRAL",
      "renditionMap" : { },
      "type" : "component"
    }, {
      "componentAttributes" : {
        "canChangeSorting" : false,
        "defaultFilter" : "",
        "defaultSortOrderHomeFeed" : "Relevance",
        "defaultSortOrderTopicsFeed" : "Relevance",
        "feedDesign" : "DEFAULT",
        "hasFeedSearch" : false,
        "subjectId" : "{!recordId}",
        "type" : "Record"
      },
      "componentName" : "forceCommunity:forceCommunityFeed",
      "id" : "863b0a53-b5ec-471b-af92-8c5cc6e28133",
      "renderPriority" : "NEUTRAL",
      "renditionMap" : { },
      "type" : "component"
    } ],
    "id" : "0c4bf612-7e6e-4175-ab3f-72c72d49b3a2",
    "regionName" : "content",
    "type" : "region"
  }, {
    "components" : [ {
      "componentAttributes" : {
        "buttonAlignment" : "center",
        "buttonBgColor" : "",
        "buttonBgHoverColor" : "",
        "buttonBorderColor" : "",
        "buttonMaxWidth" : 100,
        "buttonRadius" : 0,
        "buttonTextColor" : "",
        "buttonTextHoverColor" : "",
        "recordId" : "{!recordId}",
        "showNotificationMenu" : false
      },
      "componentName" : "forceCommunity:follow",
      "id" : "4bb69511-b627-4b28-b897-49e67c94619f",
      "renderPriority" : "NEUTRAL",
      "renditionMap" : { },
      "type" : "component"
    }, {
      "componentAttributes" : {
        "numberOfItems" : 5,
        "showViewCounts" : true,
        "title" : "Related Articles"
      },
      "componentName" : "selfService:similarArticles42",
      "id" : "3312a9e8-e9e3-44d1-bfc6-bd69390f702f",
      "renderPriority" : "NEUTRAL",
      "renditionMap" : { },
      "type" : "component"
    }, {
      "componentAttributes" : {
        "numberOfArticles" : 5,
        "title" : "Trending Articles",
        "topicId" : "{!topicId}"
      },
      "componentName" : "selfService:topicTrendingArticles42",
      "id" : "c1a7586b-b9f4-4988-be4c-bdf5b617cd39",
      "renderPriority" : "NEUTRAL",
      "renditionMap" : { },
      "type" : "component"
    } ],
    "id" : "b26e0aef-7f37-468e-b379-40ec65629041",
    "regionName" : "sidebar",
    "type" : "region"
  }, {
    "id" : "7a428ec9-6657-487b-beba-4637b4392664",
    "regionName" : "footer",
    "type" : "region"
  }, {
    "components" : [ {
      "componentAttributes" : {
        "customHeadTags" : "",
        "description" : "{!Record.Summary}",
        "title" : "{!Record._Title}"
      },
      "componentName" : "forceCommunity:seoAssistant",
      "id" : "8526e9ac-3c78-48ae-8035-40814cc863f6",
      "renditionMap" : { },
      "type" : "component"
    } ],
    "id" : "c7004557-61bd-4b66-89c6-b0b703b77e79",
    "regionName" : "sfdcHiddenRegion",
    "type" : "region"
  } ],
  "themeLayoutType" : "Inner",
  "type" : "view",
  "viewType" : "article"
}