{
  "appPageId" : "199817ad-97f1-4978-8428-c37fa787150b",
  "componentName" : "siteforce:sldsOneColLayout",
  "dataProviders" : [ ],
  "id" : "fcbc64bf-5565-4e64-a1da-c2624c401754",
  "label" : "Record Detail",
  "regions" : [ {
    "id" : "32307ed0-44fb-4cd4-a086-99f820fe238b",
    "regionName" : "header",
    "type" : "region"
  }, {
    "components" : [ {
      "componentAttributes" : {
        "recordId" : "{!recordId}"
      },
      "componentName" : "forceCommunity:recordHeadline",
      "id" : "733359bd-a6a8-4d14-8af0-dae1928af4ad",
      "renderPriority" : "NEUTRAL",
      "renditionMap" : { },
      "type" : "component"
    }, {
      "componentAttributes" : {
        "detailsTabLabel" : "Details",
        "discussionsTabLabel" : "Feed",
        "recordId" : "{!recordId}",
        "relatedTabLabel" : "Related",
        "showLegacyActivityComposer" : false,
        "tab1Type" : "details",
        "tab2Type" : "related",
        "tab3Type" : "chatter",
        "tab4Type" : "none",
        "timelineTabLabel" : "Activity"
      },
      "componentName" : "forceCommunity:recordHomeTabs",
      "id" : "bfa590f9-93e3-4bec-8919-830637e9ac7c",
      "renderPriority" : "NEUTRAL",
      "renditionMap" : { },
      "type" : "component"
    } ],
    "id" : "5a7e439e-95cb-4e6a-9caf-c193aed34c23",
    "regionName" : "content",
    "type" : "region"
  }, {
    "id" : "87e88abb-fe75-466b-8160-65c7a65939e4",
    "regionName" : "footer",
    "type" : "region"
  }, {
    "components" : [ {
      "componentAttributes" : {
        "customHeadTags" : "",
        "description" : "",
        "title" : "{!Record._Object}: {!Record._Title}"
      },
      "componentName" : "forceCommunity:seoAssistant",
      "id" : "13223218-e7e6-490d-9ef2-f4ed6dcd8e8b",
      "renditionMap" : { },
      "type" : "component"
    } ],
    "id" : "b01df2a7-b325-44b0-9e30-3e3a0b45d603",
    "regionName" : "sfdcHiddenRegion",
    "type" : "region"
  } ],
  "themeLayoutType" : "Inner",
  "type" : "view",
  "viewType" : "detail"
}