{
  "appPageId" : "b698cf55-806b-4deb-b2e3-3c2c1b01af5c",
  "componentName" : "siteforce:dynamicLayout",
  "dataProviders" : [ ],
  "id" : "d6a0e4b8-0de3-4933-b873-71cb70ab73a9",
  "label" : "View Accounts",
  "regions" : [ {
    "components" : [ {
      "componentAttributes" : {
        "background" : "background: rgba(0,0,0,0)",
        "backgroundOverlay" : "rgba(0,0,0,0.5)",
        "contentAreaWidth" : 100,
        "sectionConfig" : {
          "UUID" : "2d99f831-4252-46b8-9490-2dfa5de91be5",
          "columns" : [ {
            "UUID" : "6af07406-4f8a-44d7-9451-73c6ead39487",
            "columnKey" : "col1",
            "columnName" : "Account List Column",
            "columnWidth" : "12",
            "seedComponents" : [ {
              "attributes" : {
                "filterName" : "Recent",
                "scope" : "Account",
                "sfdc:identifier" : "forceCommunity_objectHome_account"
              },
              "fqn" : "forceCommunity:objectHome"
            } ]
          } ]
        },
        "sectionHeight" : 32
      },
      "componentName" : "forceCommunity:section",
      "id" : "2d99f831-4252-46b8-9490-2dfa5de91be5",
      "regions" : [ {
        "components" : [ {
          "componentAttributes" : {
            "enableInlineEdit" : true,
            "filterName" : "Recent",
            "layout" : "FULL",
            "pageSize" : 25,
            "scope" : "Account",
            "showActionBar" : true,
            "showChartsPanel" : true,
            "showDisplay" : "showall",
            "showFilterPanel" : true,
            "showImageIcon" : true,
            "showManualRefreshButton" : true,
            "showObjectName" : true,
            "showPinnedList" : true,
            "showSearchBar" : true
          },
          "componentName" : "forceCommunity:objectHome",
          "id" : "c80b33af-93de-412e-99c0-de6aec0c211e",
          "renderPriority" : "NEUTRAL",
          "renditionMap" : { },
          "type" : "component"
        } ],
        "id" : "6af07406-4f8a-44d7-9451-73c6ead39487",
        "regionLabel" : "Account List Column",
        "regionName" : "col1",
        "renditionMap" : { },
        "type" : "region"
      } ],
      "renderPriority" : "NEUTRAL",
      "renditionMap" : { },
      "type" : "component"
    } ],
    "id" : "4f11d45c-340e-4b32-8eaa-753c3b6c82e7",
    "regionName" : "content",
    "type" : "region"
  } ],
  "themeLayoutType" : "Inner",
  "type" : "view",
  "viewType" : "account-list"
}