{
  "appPageId" : "856d3934-99ff-4071-a05e-f35d8c6a5bc0",
  "componentName" : "siteforce:sldsOneColLayout",
  "dataProviders" : [ ],
  "id" : "941c4e06-2812-4843-807a-7bb552c29f0c",
  "label" : "Dashboard Related List",
  "regions" : [ {
    "id" : "ff09f729-0e5a-44bb-835e-0dd102769c68",
    "regionName" : "header",
    "type" : "region"
  }, {
    "components" : [ {
      "componentAttributes" : {
        "customTitle" : "",
        "parentRecordId" : "{!recordId}",
        "relatedListName" : "{!relationshipApiName}",
        "showBreadCrumbs" : true,
        "showCustomTitle" : false,
        "showManualRefreshButton" : true,
        "showRowNumbers" : true
      },
      "componentName" : "forceCommunity:relatedList",
      "id" : "bb0a3643-4705-47d4-bfe9-3d2b9aad1624",
      "renderPriority" : "NEUTRAL",
      "renditionMap" : { },
      "type" : "component"
    } ],
    "id" : "ad3f971a-b0c9-4e55-9005-4d0d273727b2",
    "regionName" : "content",
    "type" : "region"
  }, {
    "id" : "680b889d-d295-45e4-bf6e-09553813b3ec",
    "regionName" : "footer",
    "type" : "region"
  } ],
  "themeLayoutType" : "Inner",
  "type" : "view",
  "viewType" : "relatedlist-01Z"
}